{
  "fetched_at": "2026-02-01T23:00:55.132Z",
  "source": "https://www.grousemountain.com/current_conditions",
  "report_time_text": "1:30 PM Report",
  "lifts": {
    "Olympic Express High-Speed Quad Chair": "closed",
    "Peak Quad Chair": "open",
    "Screaming Eagle High-Speed Quad Chair": "closed",
    "Greenway Quad Chair": "open",
    "Magic Carpet": "open",
    "Short Cut Handle Tow": "closed"
  },
  "trails": {
    "Chalet Road": "closed",
    "Paradise": "open",
    "Ski Wee": "open",
    "The Cut": "closed",
    "Blue Face": "closed",
    "Centennial": "closed",
    "Deliverance": "closed",
    "Dogleg": "closed",
    "Expo": "closed",
    "Heaven's Sake": "open",
    "Lower Buckhorn": "closed",
    "Lower Peak": "open",
    "Lower Side Cut": "closed",
    "Paper Trail": "closed",
    "Peak": "open",
    "Side Cut": "closed",
    "Skyline": "closed",
    "Tyee Chute": "closed",
    "Upper Buckhorn": "closed",
    "Blazes": "closed",
    "Coffin": "closed",
    "Hades": "closed",
    "Inferno": "closed",
    "Outer Limits": "closed",
    "Devil's Advocate": "closed",
    "Purgatory": "open",
    "Peak Glades": "closed",
    "Grinder Tracks": "closed",
    "Expo Glades": "closed",
    "Coola's Corner": "closed",
    "Chimney": "closed",
    "Upper Blazes": "closed",
    "Mountain Highway": "closed",
    "No Man's Land": "open"
  }
}